topsis_Sarthak_401903029/__init__.py
topsis_Sarthak_401903029/topsis_Sarthak_401903029.py
Topsis_Sarthak_401903029-1.0.1.dist-info/LICENSE.txt
Topsis_Sarthak_401903029-1.0.1.dist-info/METADATA
Topsis_Sarthak_401903029-1.0.1.dist-info/WHEEL
Topsis_Sarthak_401903029-1.0.1.dist-info/entry_points.txt
Topsis_Sarthak_401903029-1.0.1.dist-info/top_level.txt
Topsis_Sarthak_401903029-1.0.1.dist-info/RECORD
